odoo/addons/mail_environment/README.rst
odoo/addons/mail_environment/__init__.py
odoo/addons/mail_environment/__manifest__.py
odoo/addons/mail_environment/i18n/de.po
odoo/addons/mail_environment/i18n/es.po
odoo/addons/mail_environment/i18n/hr.po
odoo/addons/mail_environment/i18n/mail_environment.pot
odoo/addons/mail_environment/i18n/pt_BR.po
odoo/addons/mail_environment/i18n/sl.po
odoo/addons/mail_environment/i18n/zh_CN.po
odoo/addons/mail_environment/models/__init__.py
odoo/addons/mail_environment/models/fetchmail_server.py
odoo/addons/mail_environment/models/ir_mail_server.py
odoo/addons/mail_environment/readme/CONFIGURE.rst
odoo/addons/mail_environment/readme/CONTRIBUTORS.rst
odoo/addons/mail_environment/readme/DESCRIPTION.rst
odoo/addons/mail_environment/readme/INSTALL.rst
odoo/addons/mail_environment/readme/ROADMAP.rst
odoo/addons/mail_environment/readme/USAGE.rst
odoo/addons/mail_environment/static/description/icon.png
odoo/addons/mail_environment/static/description/index.html
odoo12_addon_mail_environment-12.0.1.0.0.99.dev7.dist-info/METADATA
odoo12_addon_mail_environment-12.0.1.0.0.99.dev7.dist-info/WHEEL
odoo12_addon_mail_environment-12.0.1.0.0.99.dev7.dist-info/top_level.txt
odoo12_addon_mail_environment-12.0.1.0.0.99.dev7.dist-info/RECORD
